aiomojang/__init__.py
aiomojang/api.py
aiomojang/auth.py
aiomojang/exceptions.py
aiomojang/misc.py
aiomojang/renders.py
aiomojang/status.py
aiomojang-0.6.dist-info/LICENSE
aiomojang-0.6.dist-info/METADATA
aiomojang-0.6.dist-info/WHEEL
aiomojang-0.6.dist-info/top_level.txt
aiomojang-0.6.dist-info/RECORD
