Metadata-Version: 2.1
Name: aiomojang
Version: 0.6
Summary: An asynchronous Python wrapper for Mojang's API
Home-page: https://github.com/capslock321/aiomojang/
Author: capslock321
License: UNKNOWN
Platform: UNKNOWN
Classifier: Programming Language :: Python :: 3
Classifier: License :: OSI Approved :: MIT License
Classifier: Operating System :: OS Independent
Requires-Python: >=3.6
